{
  "$schema": "https://mintlify.com/schema.json",
  "name": "SlackHive",
  "logo": {
    "light": "/logo/light.svg",
    "dark": "/logo/dark.svg"
  },
  "favicon": "/favicon.svg",
  "colors": {
    "primary": "#D97757",
    "light": "#E89070",
    "dark": "#C06040"
  },
  "topbarLinks": [
    {
      "name": "GitHub",
      "url": "https://github.com/pelago-labs/slackhive"
    }
  ],
  "topbarCtaButton": {
    "name": "Get Started",
    "url": "https://github.com/pelago-labs/slackhive"
  },
  "navigation": [
    {
      "group": "Getting Started",
      "pages": ["introduction", "quickstart"]
    },
    {
      "group": "Configuration",
      "pages": [
        "configuration/env-vars",
        "configuration/slack-app",
        "configuration/mcp-servers"
      ]
    },
    {
      "group": "Agents",
      "pages": [
        "agents/creating-agents",
        "agents/boss-agents",
        "agents/memory",
        "agents/tools"
      ]
    },
    {
      "group": "Features",
      "pages": [
        "features/logs",
        "features/history",
        "features/users"
      ]
    },
    {
      "group": "Self-Hosting",
      "pages": [
        "self-hosting/docker",
        "self-hosting/production"
      ]
    }
  ],
  "footerSocials": {
    "github": "https://github.com/pelago-labs/slackhive"
  }
}
